leto/__init__.py
leto/run.py
leto/common/__init__.py
leto/common/config.py
leto/common/const.py
leto/core/__init__.py
leto/core/clone.py
leto/core/crawler.py
leto/core/db.py
leto/core/scheduler.py
leto/util/__init__.py
leto/util/base.py
leto/util/decorator.py
leto/util/logger.py
leto-0.1.3.dist-info/LICENSE
leto-0.1.3.dist-info/METADATA
leto-0.1.3.dist-info/WHEEL
leto-0.1.3.dist-info/entry_points.txt
leto-0.1.3.dist-info/top_level.txt
leto-0.1.3.dist-info/RECORD
